{
  "id": "61",
  "name": "죽정주공삼거리",
  "alias": [],
  "type": "삼거리",
  "manufacturer": "한진이엔씨",
  "controller_model": "",
  "dat": {
    "filename": "죽정주공삼거리.dat",
    "original_filename": "92_죽정주공삼거리.dat",
    "size": 16265,
    "manufacturer_detected": "한진이엔씨",
    "format": "remote_data_v3.5.2.0",
    "date_modified": null,
    "phone": null,
    "phases": 0,
    "plans": []
  },
  "cycle_table": null,
  "location": {
    "lat": null,
    "lng": null,
    "address": ""
  },
  "routes": [],
  "status": "정상",
  "notes": "",
  "history": [
    {
      "date": "2026-02-13",
      "action": "자동 분류 (classify.py)",
      "by": "system"
    }
  ],
  "_classification": {
    "source_files": [
      "92_죽정주공삼거리.dat",
      "92_죽정주공삼거리.dat"
    ],
    "selected": "92_죽정주공삼거리.dat",
    "reason": "주기표 매칭 없음",
    "confidence": "low"
  }
}